sema/__init__.py
sema/bench/__init__.py
sema/bench/core.py
sema/bench/dispatcher.py
sema/bench/handler.py
sema/bench/README.md
sema/bench/task.py
sema/commons/__init__.py
sema/commons/clean/__init__.py
sema/commons/clean/clean.py
sema/commons/clean/README.md
sema/commons/cli/__init__.py
sema/commons/cli/clitools.py
sema/commons/cli/README.md
sema/commons/env/README.md
sema/commons/fileformats/__init__.py
sema/commons/fileformats/mimetypes.py
sema/commons/fileformats/rdffiles.py
sema/commons/j2/__init__.py
sema/commons/j2/exceptions.py
sema/commons/j2/j2_functions.py
sema/commons/j2/rdf_syntax_builder.py
sema/commons/j2/README.md
sema/commons/j2/syntax_builder.py
sema/commons/j2-template/README.md
sema/commons/log/__init__.py
sema/commons/log/debug_logconf.yml
sema/commons/log/loader.py
sema/commons/log/README.md
sema/commons/path/README.md
sema/commons/prov/README.md
sema/commons/service/__init__.py
sema/commons/service/model.py
sema/commons/service/README.md
sema/commons/store/__init__.py
sema/commons/store/build.py
sema/commons/store/README.md
sema/commons/store/store.py
sema/commons/web/__init__.py
sema/commons/web/conneg.py
sema/commons/web/conneg_cli.py
sema/commons/web/download_to_file.py
sema/commons/web/httpsession.py
sema/discovery/__init__.py
sema/discovery/__main__.py
sema/discovery/discovery.py
sema/discovery/linkheaders.py
sema/discovery/lod_html_parser.py
sema/discovery/README.md
sema/harvest/__init__.py
sema/harvest/__main__.py
sema/harvest/config_build.py
sema/harvest/execution_report.py
sema/harvest/executor.py
sema/harvest/helper.py
sema/harvest/path_assertion.py
sema/harvest/README.md
sema/harvest/service.py
sema/harvest/store.py
sema/harvest/templates/execution_report.ttl
sema/harvest/templates/trajectory.sparql
sema/harvest/url_to_graph.py
sema/query/__init__.py
sema/query/__main__.py
sema/query/exceptions.py
sema/query/query.py
sema/query/README.md
sema/query/sparql_templates/all.sparql
sema/query/sparql_templates/bodc-find.sparql
pysema-0.1.0.dist-info/entry_points.txt
pysema-0.1.0.dist-info/LICENSE
pysema-0.1.0.dist-info/METADATA
pysema-0.1.0.dist-info/WHEEL
pysema-0.1.0.dist-info/RECORD
