Metadata-Version: 2.1
Name: pysema
Version: 0.1.0
Summary: Overall parent of all packages involving semantic manipulation of RDF data.
Home-page: https://github.com/vliz-be-opsci/py-sema
License: MIT
Author: cedricdcc
Author-email: 30471340+cedricdcc@users.noreply.github.com
Maintainer: cedricdcc
Maintainer-email: 30471340+cedricdcc@users.noreply.github.com
Requires-Python: >=3.10,<4.0
Classifier: License :: OSI Approved :: MIT License
Classifier: Programming Language :: Python :: 3
Classifier: Programming Language :: Python :: 3.10
Classifier: Programming Language :: Python :: 3.11
Classifier: Programming Language :: Python :: 3.12
Requires-Dist: apscheduler (>=3.10.4,<4.0.0)
Requires-Dist: jinja2 (>=3.1.4,<4.0.0)
Requires-Dist: pyshacl (>=0.26.0,<0.27.0)
Requires-Dist: python-dateutil (>=2.9.0.post0,<3.0.0)
Requires-Dist: pyyaml (>=6.0.2,<7.0.0)
Requires-Dist: rdflib (>=7.0.0,<8.0.0)
Requires-Dist: requests (>=2.32.3,<3.0.0)
Requires-Dist: setuptools
Requires-Dist: typeguard (>=4.3.0,<5.0.0)
Requires-Dist: uritemplate (>=4.1.1,<5.0.0)
Requires-Dist: urllib3 (>=2.2.2,<3.0.0)
Requires-Dist: urnparse (>=0.2.2,<0.3.0)
Requires-Dist: validators (>=0.28.3,<0.29.0)
Requires-Dist: watchdog (>=4.0.1,<5.0.0)
Project-URL: Repository, https://github.com/vliz-be-opsci/py-sema
